{
  "schemaVersion": 1,
  "id": "drippyloadingscreen",
  "version": "1.5.0",
  "name": "Drippy Loading Screen",
  "description": "Drippy Loading Screen © Copyright 2021 Keksuccino. Drippy Loading Screen is licensed under DSMSL (DON'T SNATCH MA STUFF LICENSE). See https://github.com/Keksuccino/Drippy-Loading-Screen/blob/main/LICENSE.md for more information about this license.",
  "environment": "client",
  "authors": [
    "Keksuccino"
  ],
  "contributors": [],
  "contact": {},
  "license": "DSMSL (DON'T SNATCH MA STUFF LICENSE)",
  "icon": "assets/drippyloadingscreen/icon.png",
  "entrypoints": {
    "main": [
      "de.keksuccino.drippyloadingscreen.DrippyLoadingScreen"
    ],
    "client": [],
    "server": []
  },
  "mixins": [
    "drippyloadingscreen.mixin.json"
  ],
  "depends": {
    "fabricloader": ">=0.12.6",
    "konkrete": ">=1.3.3",
    "fabric": "*",
	"minecraft": "1.18.x",
    "java": ">=17"
  }
}